kivy_deps/__init__.py
kivy_deps/sdl2_dev/__init__.py
kivy_deps.sdl2_dev-0.8.0.data/data/include/SDL2/SDL.h
kivy_deps.sdl2_dev-0.8.0.data/data/include/SDL2/SDL_assert.h
kivy_deps.sdl2_dev-0.8.0.data/data/include/SDL2/SDL_atomic.h
kivy_deps.sdl2_dev-0.8.0.data/data/include/SDL2/SDL_audio.h
kivy_deps.sdl2_dev-0.8.0.data/data/include/SDL2/SDL_bits.h
kivy_deps.sdl2_dev-0.8.0.data/data/include/SDL2/SDL_blendmode.h
kivy_deps.sdl2_dev-0.8.0.data/data/include/SDL2/SDL_clipboard.h
kivy_deps.sdl2_dev-0.8.0.data/data/include/SDL2/SDL_config.h
kivy_deps.sdl2_dev-0.8.0.data/data/include/SDL2/SDL_cpuinfo.h
kivy_deps.sdl2_dev-0.8.0.data/data/include/SDL2/SDL_egl.h
kivy_deps.sdl2_dev-0.8.0.data/data/include/SDL2/SDL_endian.h
kivy_deps.sdl2_dev-0.8.0.data/data/include/SDL2/SDL_error.h
kivy_deps.sdl2_dev-0.8.0.data/data/include/SDL2/SDL_events.h
kivy_deps.sdl2_dev-0.8.0.data/data/include/SDL2/SDL_filesystem.h
kivy_deps.sdl2_dev-0.8.0.data/data/include/SDL2/SDL_gamecontroller.h
kivy_deps.sdl2_dev-0.8.0.data/data/include/SDL2/SDL_gesture.h
kivy_deps.sdl2_dev-0.8.0.data/data/include/SDL2/SDL_guid.h
kivy_deps.sdl2_dev-0.8.0.data/data/include/SDL2/SDL_haptic.h
kivy_deps.sdl2_dev-0.8.0.data/data/include/SDL2/SDL_hidapi.h
kivy_deps.sdl2_dev-0.8.0.data/data/include/SDL2/SDL_hints.h
kivy_deps.sdl2_dev-0.8.0.data/data/include/SDL2/SDL_image.h
kivy_deps.sdl2_dev-0.8.0.data/data/include/SDL2/SDL_joystick.h
kivy_deps.sdl2_dev-0.8.0.data/data/include/SDL2/SDL_keyboard.h
kivy_deps.sdl2_dev-0.8.0.data/data/include/SDL2/SDL_keycode.h
kivy_deps.sdl2_dev-0.8.0.data/data/include/SDL2/SDL_loadso.h
kivy_deps.sdl2_dev-0.8.0.data/data/include/SDL2/SDL_locale.h
kivy_deps.sdl2_dev-0.8.0.data/data/include/SDL2/SDL_log.h
kivy_deps.sdl2_dev-0.8.0.data/data/include/SDL2/SDL_main.h
kivy_deps.sdl2_dev-0.8.0.data/data/include/SDL2/SDL_messagebox.h
kivy_deps.sdl2_dev-0.8.0.data/data/include/SDL2/SDL_metal.h
kivy_deps.sdl2_dev-0.8.0.data/data/include/SDL2/SDL_misc.h
kivy_deps.sdl2_dev-0.8.0.dist-info/METADATA
kivy_deps.sdl2_dev-0.8.0.dist-info/WHEEL
kivy_deps.sdl2_dev-0.8.0.dist-info/top_level.txt
kivy_deps.sdl2_dev-0.8.0.dist-info/RECORD
